<?xml version = '1.0' encoding = 'UTF-8'?>
<FKIndexAssociation class="oracle.dbtools.crest.model.design.relational.FKIndexAssociation" directorySegmentName="seg_6" id="1C28C4A0-C2C8-A9F6-DAF8-73D610F69A84" containerWithKeyObject="342D1FA1-A85A-B032-7C04-2F644B47B971" localFKIndex="E0139560-48EB-A72E-9D30-98FD83E3B0B7" name="docu_tran_moci_fk">
<sourceConnName>postgres</sourceConnName>
<sourceObjSchema>public</sourceObjSchema>
<sourceObjName>docu_tran_moci_fk</sourceObjName>
<createdBy>systech59</createdBy>
<createdTime>2023-02-07 03:16:00 UTC</createdTime>
<ownerDesignName>suite</ownerDesignName>
<referredTableLongName>public.monedas</referredTableLongName>
<deleteRule>NO ACTION</deleteRule>
<referredTableID>49C32E40-5ED5-EEEB-3804-FD451607B205</referredTableID>
<keyObject>57AA94A8-2832-B6AD-90E6-277620DCF929</keyObject>
<referredKeyID>57AA94A8-2832-B6AD-90E6-277620DCF929</referredKeyID>
<mandatory>true</mandatory>
<refColNames>moneda</refColNames>
<transferable>true</transferable>
<rely>false</rely>
<columnDependencyConstraintGenerateInDDL>true</columnDependencyConstraintGenerateInDDL>
</FKIndexAssociation>