<?xml version = '1.0' encoding = 'UTF-8'?>
<TableProxyOraclev11g class="oracle.dbtools.crest.model.design.storage.oracle.v11g.TableProxyOraclev11g" name="festivos" directorySegmentName="seg_5" id="B8BE25C9-64D4-79D2-E631-7DF6A59C452C">
<createdBy>systech59</createdBy>
<createdTime>2023-02-07 03:16:08 UTC</createdTime>
<ownerDesignName>suite</ownerDesignName>
<schemaObject>4996015A-2053-30D5-BD5A-1522554E1A37</schemaObject>
<logging>YES</logging>
<partitionedRowMovement>DISABLE</partitionedRowMovement>
<temporaryChanged>false</temporaryChanged>
<accessDriverType>oracle_loader</accessDriverType>
<rejectLimit></rejectLimit>
<columnProxies itemClass="oracle.dbtools.crest.model.design.storage.oracle.v12c.ColumnProxyOraclev12c">
<ColumnProxy name="interfaz" id="0BC2C62A-A357-2A88-86EE-2A6477B10C27">
<createdBy>systech59</createdBy>
<createdTime>2023-02-07 03:16:07 UTC</createdTime>
<ownerDesignName>suite</ownerDesignName>
<defaultValue>(&apos;N&apos;::character varying)::decision_n_s</defaultValue>
</ColumnProxy>
<ColumnProxy name="usuario_insercion" id="7A645773-5457-1FDE-EC24-9B82C69A046D">
<createdBy>systech59</createdBy>
<createdTime>2023-02-07 03:16:07 UTC</createdTime>
<ownerDesignName>suite</ownerDesignName>
</ColumnProxy>
<ColumnProxy name="oid" id="81EBC3BF-C6D1-C194-50D7-9EBE91455A8C">
<createdBy>systech59</createdBy>
<createdTime>2023-02-07 03:16:07 UTC</createdTime>
<ownerDesignName>suite</ownerDesignName>
<defaultValue>nextval(&apos;festivos_oid_seq&apos;::regclass)</defaultValue>
</ColumnProxy>
<ColumnProxy name="nombre" id="A4B27FF8-3943-E00A-7C4B-04074B3FCD47">
<createdBy>systech59</createdBy>
<createdTime>2023-02-07 03:16:07 UTC</createdTime>
<ownerDesignName>suite</ownerDesignName>
</ColumnProxy>
<ColumnProxy name="festivo" id="BC701096-B7FF-CAE2-54FB-43E2E266EC95">
<createdBy>systech59</createdBy>
<createdTime>2023-02-07 03:16:07 UTC</createdTime>
<ownerDesignName>suite</ownerDesignName>
</ColumnProxy>
<ColumnProxy name="fecha_insercion" id="BE774A19-A91D-7282-B683-F727C4193FBC">
<createdBy>systech59</createdBy>
<createdTime>2023-02-07 03:16:07 UTC</createdTime>
<ownerDesignName>suite</ownerDesignName>
<defaultValue>now()</defaultValue>
</ColumnProxy>
</columnProxies>
<primaryKeys>
<PrimaryKey class="oracle.dbtools.crest.model.design.storage.oracle.v10g.PKProxyOraclev10g" name="fest_pk" id="6D155843-2C00-8B4A-4039-F74C3950F4C6">
<createdBy>systech59</createdBy>
<createdTime>2023-02-07 03:16:08 UTC</createdTime>
<ownerDesignName>suite</ownerDesignName>
<indexSort>SORTED</indexSort>
</PrimaryKey>
</primaryKeys>
<tableCheckConstraints itemClass="oracle.dbtools.crest.model.design.storage.oracle.TableCheckConstraintOracle">
<TableCheckConstraint name="usua_inse_ck_0159" id="B92897C2-1F23-CBDF-E55D-E7E2B7972F6A">
<createdBy>systech59</createdBy>
<createdTime>2023-02-07 03:16:08 UTC</createdTime>
<ownerDesignName>suite</ownerDesignName>
</TableCheckConstraint>
<TableCheckConstraint name="avcon_1138898360_inter_058" id="F0DFB170-902D-DFA6-29DA-EC67B8C5ED4D">
<createdBy>systech59</createdBy>
<createdTime>2023-02-07 03:16:08 UTC</createdTime>
<ownerDesignName>suite</ownerDesignName>
</TableCheckConstraint>
</tableCheckConstraints>
<uniqueKeys>
<UniqueKey class="oracle.dbtools.crest.model.design.storage.oracle.v10g.UniqueOraclev10g" name="festivos_oid" id="8F75A3FC-452C-664B-4A56-C92FE673EFFB">
<createdBy>systech59</createdBy>
<createdTime>2023-02-07 03:16:08 UTC</createdTime>
<ownerDesignName>suite</ownerDesignName>
<indexSort>SORTED</indexSort>
</UniqueKey>
</uniqueKeys>
</TableProxyOraclev11g>