<?xml version = '1.0' encoding = 'UTF-8'?>
<FKIndexAssociation class="oracle.dbtools.crest.model.design.relational.FKIndexAssociation" directorySegmentName="seg_0" id="17F00D1B-D71D-4998-4752-4DB8F8965A49" containerWithKeyObject="5F1F8491-3DF4-7EC7-F689-D70B71C8A0AC" localFKIndex="B85CD783-7DCD-27E6-B3ED-A81B496F3E7E" name="registros_personas_FK">
<createdBy>systech59</createdBy>
<createdTime>2022-06-26 00:18:17 UTC</createdTime>
<ownerDesignName>crm</ownerDesignName>
<referredTableLongName>personas</referredTableLongName>
<deleteRule>NO ACTION</deleteRule>
<referredTableID>E2A9531D-9074-A62F-C571-9C99CB1F6EE5</referredTableID>
<keyObject>220FA92D-7DFD-F67B-AC2C-B3A458315404</keyObject>
<referredKeyID>220FA92D-7DFD-F67B-AC2C-B3A458315404</referredKeyID>
<mandatory>true</mandatory>
<refColNames>id_persona</refColNames>
<transferable>true</transferable>
<rely>false</rely>
<columnDependencyConstraintGenerateInDDL>true</columnDependencyConstraintGenerateInDDL>
</FKIndexAssociation>
