<?xml version = '1.0' encoding = 'UTF-8'?>
<FKIndexAssociation class="oracle.dbtools.crest.model.design.relational.FKIndexAssociation" directorySegmentName="seg_8" id="259DEF11-198B-EA19-F843-4F41A896CE96" containerWithKeyObject="412BE129-859C-5664-FE23-9752BBB86D89" localFKIndex="F70AC053-683D-E8C7-42C8-DE6EBCB46BF6" name="inve_mone_fk">
<sourceConnName>postgres</sourceConnName>
<sourceObjSchema>public</sourceObjSchema>
<sourceObjName>inve_mone_fk</sourceObjName>
<createdBy>systech59</createdBy>
<createdTime>2023-02-07 03:16:01 UTC</createdTime>
<ownerDesignName>suite</ownerDesignName>
<referredTableLongName>public.monedas</referredTableLongName>
<deleteRule>NO ACTION</deleteRule>
<referredTableID>49C32E40-5ED5-EEEB-3804-FD451607B205</referredTableID>
<keyObject>57AA94A8-2832-B6AD-90E6-277620DCF929</keyObject>
<referredKeyID>57AA94A8-2832-B6AD-90E6-277620DCF929</referredKeyID>
<mandatory>true</mandatory>
<refColNames>moneda</refColNames>
<transferable>true</transferable>
<rely>false</rely>
<columnDependencyConstraintGenerateInDDL>true</columnDependencyConstraintGenerateInDDL>
</FKIndexAssociation>