<?xml version = '1.0' encoding = 'UTF-8'?>
<TableProxyOraclev11g class="oracle.dbtools.crest.model.design.storage.oracle.v11g.TableProxyOraclev11g" name="proveedores_restricciones" directorySegmentName="seg_4" id="90EA4A98-6C14-2592-D05A-15FA715A41FE">
<createdBy>systech59</createdBy>
<createdTime>2023-02-07 03:16:08 UTC</createdTime>
<ownerDesignName>suite</ownerDesignName>
<schemaObject>4996015A-2053-30D5-BD5A-1522554E1A37</schemaObject>
<logging>YES</logging>
<partitionedRowMovement>DISABLE</partitionedRowMovement>
<temporaryChanged>false</temporaryChanged>
<accessDriverType>oracle_loader</accessDriverType>
<rejectLimit></rejectLimit>
<columnProxies itemClass="oracle.dbtools.crest.model.design.storage.oracle.v12c.ColumnProxyOraclev12c">
<ColumnProxy name="caracteres" id="021D5EEC-C472-EF31-314E-9810C7D339DF">
<createdBy>systech59</createdBy>
<createdTime>2023-02-07 03:16:07 UTC</createdTime>
<ownerDesignName>suite</ownerDesignName>
</ColumnProxy>
<ColumnProxy name="oid" id="0B907C08-7321-318D-562F-D649D880C40B">
<createdBy>systech59</createdBy>
<createdTime>2023-02-07 03:16:07 UTC</createdTime>
<ownerDesignName>suite</ownerDesignName>
<defaultValue>nextval(&apos;proveedores_restricciones_oid_seq&apos;::regclass)</defaultValue>
</ColumnProxy>
<ColumnProxy name="proveedor" id="1ADE9235-52D3-6F8D-38E6-DA3BF23C415C">
<createdBy>systech59</createdBy>
<createdTime>2023-02-07 03:16:07 UTC</createdTime>
<ownerDesignName>suite</ownerDesignName>
</ColumnProxy>
<ColumnProxy name="fecha_insercion" id="42F924D8-628A-24BD-5BE0-B257FABBB2A5">
<createdBy>systech59</createdBy>
<createdTime>2023-02-07 03:16:07 UTC</createdTime>
<ownerDesignName>suite</ownerDesignName>
<defaultValue>now()</defaultValue>
</ColumnProxy>
<ColumnProxy name="usuario_insercion" id="4DB04019-2879-294A-26FD-D8C51227E95A">
<createdBy>systech59</createdBy>
<createdTime>2023-02-07 03:16:07 UTC</createdTime>
<ownerDesignName>suite</ownerDesignName>
</ColumnProxy>
<ColumnProxy name="campo" id="DA550C82-97D1-5D4A-79C4-18878368F3AA">
<createdBy>systech59</createdBy>
<createdTime>2023-02-07 03:16:07 UTC</createdTime>
<ownerDesignName>suite</ownerDesignName>
</ColumnProxy>
<ColumnProxy name="interfaz" id="E0A09450-D078-58A1-1E60-847E14B9CEBA">
<createdBy>systech59</createdBy>
<createdTime>2023-02-07 03:16:07 UTC</createdTime>
<ownerDesignName>suite</ownerDesignName>
<defaultValue>(&apos;N&apos;::character varying)::decision_n_s</defaultValue>
</ColumnProxy>
</columnProxies>
<indexProxies>
<IndexProxy class="oracle.dbtools.crest.model.design.storage.oracle.v10g.IndexProxyOraclev10g" name="prov_rest_prov_fk" id="642277EB-2E44-5A38-6AA5-22C39615D3D2">
<createdBy>systech59</createdBy>
<createdTime>2023-02-07 03:16:08 UTC</createdTime>
<ownerDesignName>suite</ownerDesignName>
</IndexProxy>
</indexProxies>
<foreignKeys>
<ForeignKey class="oracle.dbtools.crest.model.design.storage.oracle.v10g.FKProxyOraclev10g" name="prov_rest_prov_fk" id="95A96992-AAEA-CC42-52D1-56D454F65BA4">
<createdBy>systech59</createdBy>
<createdTime>2023-02-07 03:16:08 UTC</createdTime>
<ownerDesignName>suite</ownerDesignName>
</ForeignKey>
</foreignKeys>
<tableCheckConstraints itemClass="oracle.dbtools.crest.model.design.storage.oracle.TableCheckConstraintOracle">
<TableCheckConstraint name="prov_rest_inte_ck" id="01F18E56-E240-D441-1AFC-9692FF961C94">
<createdBy>systech59</createdBy>
<createdTime>2023-02-07 03:16:08 UTC</createdTime>
<ownerDesignName>suite</ownerDesignName>
</TableCheckConstraint>
<TableCheckConstraint name="prov_rest_usin_ck" id="587519F8-B9FC-AFF6-5734-87CD3BA492A1">
<createdBy>systech59</createdBy>
<createdTime>2023-02-07 03:16:08 UTC</createdTime>
<ownerDesignName>suite</ownerDesignName>
</TableCheckConstraint>
</tableCheckConstraints>
<uniqueKeys>
<UniqueKey class="oracle.dbtools.crest.model.design.storage.oracle.v10g.UniqueOraclev10g" name="prov_rest_ind01" id="4F5DEC15-5D07-3E29-3CAB-B5851CDFE26B">
<createdBy>systech59</createdBy>
<createdTime>2023-02-07 03:16:08 UTC</createdTime>
<ownerDesignName>suite</ownerDesignName>
<indexSort>SORTED</indexSort>
</UniqueKey>
<UniqueKey class="oracle.dbtools.crest.model.design.storage.oracle.v10g.UniqueOraclev10g" name="proveedores_restricciones_oid" id="BBAABE89-98CE-AEF7-F5D9-16726C82F41B">
<createdBy>systech59</createdBy>
<createdTime>2023-02-07 03:16:08 UTC</createdTime>
<ownerDesignName>suite</ownerDesignName>
<indexSort>SORTED</indexSort>
</UniqueKey>
</uniqueKeys>
</TableProxyOraclev11g>