<?xml version = '1.0' encoding = 'UTF-8'?>
<TableProxyOraclev11g class="oracle.dbtools.crest.model.design.storage.oracle.v11g.TableProxyOraclev11g" name="detalles_ingresos" directorySegmentName="seg_7" id="F02B0EF5-6D3A-D0E5-17DE-520B97FF4703">
<createdBy>systech59</createdBy>
<createdTime>2023-02-07 03:16:08 UTC</createdTime>
<ownerDesignName>suite</ownerDesignName>
<schemaObject>4996015A-2053-30D5-BD5A-1522554E1A37</schemaObject>
<logging>YES</logging>
<partitionedRowMovement>DISABLE</partitionedRowMovement>
<temporaryChanged>false</temporaryChanged>
<accessDriverType>oracle_loader</accessDriverType>
<rejectLimit></rejectLimit>
<columnProxies itemClass="oracle.dbtools.crest.model.design.storage.oracle.v12c.ColumnProxyOraclev12c">
<ColumnProxy name="forma_pago" id="30490DEC-FD35-B0CC-ECB5-5DE93BDB9499">
<createdBy>systech59</createdBy>
<createdTime>2023-02-07 03:16:07 UTC</createdTime>
<ownerDesignName>suite</ownerDesignName>
</ColumnProxy>
<ColumnProxy name="valor_iva" id="3764CAEC-072D-137F-4041-0B0C750D4C0B">
<createdBy>systech59</createdBy>
<createdTime>2023-02-07 03:16:07 UTC</createdTime>
<ownerDesignName>suite</ownerDesignName>
</ColumnProxy>
<ColumnProxy name="usuario" id="37A08A03-96D1-A8E9-5598-F261D3D0EBEC">
<createdBy>systech59</createdBy>
<createdTime>2023-02-07 03:16:07 UTC</createdTime>
<ownerDesignName>suite</ownerDesignName>
</ColumnProxy>
<ColumnProxy name="punto" id="37CA8F26-2DEE-19E9-4E48-9027C3F05C63">
<createdBy>systech59</createdBy>
<createdTime>2023-02-07 03:16:07 UTC</createdTime>
<ownerDesignName>suite</ownerDesignName>
</ColumnProxy>
<ColumnProxy name="usuario_insercion" id="497FCFE9-76D5-52D0-52FC-193B398A9C05">
<createdBy>systech59</createdBy>
<createdTime>2023-02-07 03:16:07 UTC</createdTime>
<ownerDesignName>suite</ownerDesignName>
</ColumnProxy>
<ColumnProxy name="fecha_apertura" id="4FBD4079-FDF0-8780-E69D-69FABE033410">
<createdBy>systech59</createdBy>
<createdTime>2023-02-07 03:16:07 UTC</createdTime>
<ownerDesignName>suite</ownerDesignName>
</ColumnProxy>
<ColumnProxy name="valor_afectar" id="51DB49F4-CF6A-6BFA-A1B7-1C1CAABD7A70">
<createdBy>systech59</createdBy>
<createdTime>2023-02-07 03:16:07 UTC</createdTime>
<ownerDesignName>suite</ownerDesignName>
</ColumnProxy>
<ColumnProxy name="oid" id="60CB5A2D-EEE3-606E-AD7B-388F72BD9435">
<createdBy>systech59</createdBy>
<createdTime>2023-02-07 03:16:07 UTC</createdTime>
<ownerDesignName>suite</ownerDesignName>
<defaultValue>nextval(&apos;detalles_ingresos_oid_seq&apos;::regclass)</defaultValue>
</ColumnProxy>
<ColumnProxy name="banco" id="6F19DE39-96E2-22A0-0A00-583D06759389">
<createdBy>systech59</createdBy>
<createdTime>2023-02-07 03:16:07 UTC</createdTime>
<ownerDesignName>suite</ownerDesignName>
</ColumnProxy>
<ColumnProxy name="valor_base" id="72C3C5E8-56CB-592C-6BB8-CE25DE65BB32">
<createdBy>systech59</createdBy>
<createdTime>2023-02-07 03:16:07 UTC</createdTime>
<ownerDesignName>suite</ownerDesignName>
</ColumnProxy>
<ColumnProxy name="cliente" id="74CDAFF4-0284-B1CD-A590-695AF40B5B8D">
<createdBy>systech59</createdBy>
<createdTime>2023-02-07 03:16:07 UTC</createdTime>
<ownerDesignName>suite</ownerDesignName>
</ColumnProxy>
<ColumnProxy name="valor_total" id="894160F5-B66F-5114-29BA-D4FC21E4CD3E">
<createdBy>systech59</createdBy>
<createdTime>2023-02-07 03:16:07 UTC</createdTime>
<ownerDesignName>suite</ownerDesignName>
</ColumnProxy>
<ColumnProxy name="plazo" id="95D540FF-B35E-E69F-B915-BE076FFB193B">
<createdBy>systech59</createdBy>
<createdTime>2023-02-07 03:16:07 UTC</createdTime>
<ownerDesignName>suite</ownerDesignName>
</ColumnProxy>
<ColumnProxy name="secuepertenece_recaudo_ingreso" id="A9ADE4E4-69A8-E29C-895B-D13788712226">
<createdBy>systech59</createdBy>
<createdTime>2023-02-07 03:16:07 UTC</createdTime>
<ownerDesignName>suite</ownerDesignName>
</ColumnProxy>
<ColumnProxy name="referencia" id="AA843E81-1D4B-02AE-E396-DACC232948C3">
<createdBy>systech59</createdBy>
<createdTime>2023-02-07 03:16:07 UTC</createdTime>
<ownerDesignName>suite</ownerDesignName>
</ColumnProxy>
<ColumnProxy name="interfaz" id="BB3243D0-73B6-222A-AD0E-6DAD58C0DE14">
<createdBy>systech59</createdBy>
<createdTime>2023-02-07 03:16:07 UTC</createdTime>
<ownerDesignName>suite</ownerDesignName>
<defaultValue>(&apos;N&apos;::character varying)::decision_n_s</defaultValue>
</ColumnProxy>
<ColumnProxy name="autorizacion" id="C4E58659-C465-C2EB-ABB4-8D39ABA490B4">
<createdBy>systech59</createdBy>
<createdTime>2023-02-07 03:16:07 UTC</createdTime>
<ownerDesignName>suite</ownerDesignName>
</ColumnProxy>
<ColumnProxy name="recaudo" id="C7E7A8BD-AD44-F50E-DE67-6939A1EC4C23">
<createdBy>systech59</createdBy>
<createdTime>2023-02-07 03:16:07 UTC</createdTime>
<ownerDesignName>suite</ownerDesignName>
</ColumnProxy>
<ColumnProxy name="secuencia" id="D42FBAB0-B255-DEBD-C90C-4790375D1F44">
<createdBy>systech59</createdBy>
<createdTime>2023-02-07 03:16:07 UTC</createdTime>
<ownerDesignName>suite</ownerDesignName>
</ColumnProxy>
<ColumnProxy name="caja" id="DD475945-3099-0F94-C555-6D6C74BCFCC0">
<createdBy>systech59</createdBy>
<createdTime>2023-02-07 03:16:07 UTC</createdTime>
<ownerDesignName>suite</ownerDesignName>
</ColumnProxy>
<ColumnProxy name="fecha_insercion" id="E4F23651-498F-9B75-EF99-492DCAD92E11">
<createdBy>systech59</createdBy>
<createdTime>2023-02-07 03:16:07 UTC</createdTime>
<ownerDesignName>suite</ownerDesignName>
<defaultValue>now()</defaultValue>
</ColumnProxy>
<ColumnProxy name="tarjeta" id="EF8EE3B2-F345-BB6B-9BD5-21FF7B4F33AE">
<createdBy>systech59</createdBy>
<createdTime>2023-02-07 03:16:07 UTC</createdTime>
<ownerDesignName>suite</ownerDesignName>
</ColumnProxy>
</columnProxies>
<indexProxies>
<IndexProxy class="oracle.dbtools.crest.model.design.storage.oracle.v10g.IndexProxyOraclev10g" name="deta_ingr_tarj_fk" id="0799815A-94AE-2DA2-9FBB-D5551AB983C0">
<createdBy>systech59</createdBy>
<createdTime>2023-02-07 03:16:07 UTC</createdTime>
<ownerDesignName>suite</ownerDesignName>
</IndexProxy>
<IndexProxy class="oracle.dbtools.crest.model.design.storage.oracle.v10g.IndexProxyOraclev10g" name="deta_ingr_form_pago_fk" id="1EEFF0CE-9389-A8B4-581D-445876AC777C">
<createdBy>systech59</createdBy>
<createdTime>2023-02-07 03:16:07 UTC</createdTime>
<ownerDesignName>suite</ownerDesignName>
</IndexProxy>
<IndexProxy class="oracle.dbtools.crest.model.design.storage.oracle.v10g.IndexProxyOraclev10g" name="deta_ingr_banc_fk" id="2B9D77E4-141D-B9B4-CBB1-873A8DF6CBF4">
<createdBy>systech59</createdBy>
<createdTime>2023-02-07 03:16:07 UTC</createdTime>
<ownerDesignName>suite</ownerDesignName>
</IndexProxy>
<IndexProxy class="oracle.dbtools.crest.model.design.storage.oracle.v10g.IndexProxyOraclev10g" name="deta_ingr_cont_caja_fk" id="38AB8F31-0440-C3AD-D4EE-4250ED626BEA">
<createdBy>systech59</createdBy>
<createdTime>2023-02-07 03:16:07 UTC</createdTime>
<ownerDesignName>suite</ownerDesignName>
</IndexProxy>
<IndexProxy class="oracle.dbtools.crest.model.design.storage.oracle.v10g.IndexProxyOraclev10g" name="deta_ingr_clie_fk" id="3E2C6331-DEDD-EFC9-BA35-7CF19288E75C">
<createdBy>systech59</createdBy>
<createdTime>2023-02-07 03:16:07 UTC</createdTime>
<ownerDesignName>suite</ownerDesignName>
</IndexProxy>
<IndexProxy class="oracle.dbtools.crest.model.design.storage.oracle.v10g.IndexProxyOraclev10g" name="deta_ingr_reca_ingr_fk" id="520DDEE9-47C9-FC63-FDBB-748FB9F9AE20">
<createdBy>systech59</createdBy>
<createdTime>2023-02-07 03:16:07 UTC</createdTime>
<ownerDesignName>suite</ownerDesignName>
</IndexProxy>
</indexProxies>
<foreignKeys>
<ForeignKey class="oracle.dbtools.crest.model.design.storage.oracle.v10g.FKProxyOraclev10g" name="deta_ingr_cont_caja_fk" id="005CB97D-F379-6508-B0DE-F17679C2CF1C">
<createdBy>systech59</createdBy>
<createdTime>2023-02-07 03:16:08 UTC</createdTime>
<ownerDesignName>suite</ownerDesignName>
</ForeignKey>
<ForeignKey class="oracle.dbtools.crest.model.design.storage.oracle.v10g.FKProxyOraclev10g" name="deta_ingr_form_pago_fk" id="121DE9BD-02C9-C407-2133-256DFFF9DC6A">
<createdBy>systech59</createdBy>
<createdTime>2023-02-07 03:16:08 UTC</createdTime>
<ownerDesignName>suite</ownerDesignName>
</ForeignKey>
<ForeignKey class="oracle.dbtools.crest.model.design.storage.oracle.v10g.FKProxyOraclev10g" name="deta_ingr_banc_fk" id="71E5DA8C-678C-5276-3533-EB38D12FD185">
<createdBy>systech59</createdBy>
<createdTime>2023-02-07 03:16:08 UTC</createdTime>
<ownerDesignName>suite</ownerDesignName>
</ForeignKey>
<ForeignKey class="oracle.dbtools.crest.model.design.storage.oracle.v10g.FKProxyOraclev10g" name="deta_ingr_tarj_fk" id="8BA6A578-9BDF-652E-CBF5-67F83B83A625">
<createdBy>systech59</createdBy>
<createdTime>2023-02-07 03:16:08 UTC</createdTime>
<ownerDesignName>suite</ownerDesignName>
</ForeignKey>
<ForeignKey class="oracle.dbtools.crest.model.design.storage.oracle.v10g.FKProxyOraclev10g" name="deta_ingr_clie_fk" id="BB8231E0-F1D0-E255-C5A7-0CF219C8E1B7">
<createdBy>systech59</createdBy>
<createdTime>2023-02-07 03:16:08 UTC</createdTime>
<ownerDesignName>suite</ownerDesignName>
</ForeignKey>
<ForeignKey class="oracle.dbtools.crest.model.design.storage.oracle.v10g.FKProxyOraclev10g" name="deta_ingr_reca_ingr_fk" id="CA2D13E0-5A50-DDF6-C7A7-41DF1FC6C14E">
<createdBy>systech59</createdBy>
<createdTime>2023-02-07 03:16:08 UTC</createdTime>
<ownerDesignName>suite</ownerDesignName>
</ForeignKey>
</foreignKeys>
<primaryKeys>
<PrimaryKey class="oracle.dbtools.crest.model.design.storage.oracle.v10g.PKProxyOraclev10g" name="deta_ingr_pk" id="F0D21948-47F5-3972-5C4E-BC5B0695BBCE">
<createdBy>systech59</createdBy>
<createdTime>2023-02-07 03:16:08 UTC</createdTime>
<ownerDesignName>suite</ownerDesignName>
<indexSort>SORTED</indexSort>
</PrimaryKey>
</primaryKeys>
<tableCheckConstraints itemClass="oracle.dbtools.crest.model.design.storage.oracle.TableCheckConstraintOracle">
<TableCheckConstraint name="avcon_1138898359_inter_120" id="0CD1D535-9AC7-DF00-1A7B-E8652FE65406">
<createdBy>systech59</createdBy>
<createdTime>2023-02-07 03:16:08 UTC</createdTime>
<ownerDesignName>suite</ownerDesignName>
</TableCheckConstraint>
<TableCheckConstraint name="usua_inse_ck_0114" id="F1D3F985-BE34-0283-9A1B-9DAC7B691057">
<createdBy>systech59</createdBy>
<createdTime>2023-02-07 03:16:08 UTC</createdTime>
<ownerDesignName>suite</ownerDesignName>
</TableCheckConstraint>
</tableCheckConstraints>
<uniqueKeys>
<UniqueKey class="oracle.dbtools.crest.model.design.storage.oracle.v10g.UniqueOraclev10g" name="detalles_ingresos_oid" id="19CC85D5-7D43-9983-4643-25454887265B">
<createdBy>systech59</createdBy>
<createdTime>2023-02-07 03:16:08 UTC</createdTime>
<ownerDesignName>suite</ownerDesignName>
<indexSort>SORTED</indexSort>
</UniqueKey>
</uniqueKeys>
</TableProxyOraclev11g>