<?xml version = '1.0' encoding = 'UTF-8'?>
<TableProxyOraclev11g class="oracle.dbtools.crest.model.design.storage.oracle.v11g.TableProxyOraclev11g" name="transacciones_anulaciones" directorySegmentName="seg_2" id="4B5310DC-F8A3-1246-B769-73F3675E895D">
<createdBy>systech59</createdBy>
<createdTime>2023-02-07 03:16:08 UTC</createdTime>
<ownerDesignName>suite</ownerDesignName>
<schemaObject>4996015A-2053-30D5-BD5A-1522554E1A37</schemaObject>
<logging>YES</logging>
<partitionedRowMovement>DISABLE</partitionedRowMovement>
<temporaryChanged>false</temporaryChanged>
<accessDriverType>oracle_loader</accessDriverType>
<rejectLimit></rejectLimit>
<columnProxies itemClass="oracle.dbtools.crest.model.design.storage.oracle.v12c.ColumnProxyOraclev12c">
<ColumnProxy name="transaccion_anulacion" id="2828CC3E-3501-88B8-A597-BECBACA45E24">
<createdBy>systech59</createdBy>
<createdTime>2023-02-07 03:16:07 UTC</createdTime>
<ownerDesignName>suite</ownerDesignName>
</ColumnProxy>
<ColumnProxy name="fecha_insercion" id="34910678-90DB-62E7-7FD4-5EEC6B75775C">
<createdBy>systech59</createdBy>
<createdTime>2023-02-07 03:16:07 UTC</createdTime>
<ownerDesignName>suite</ownerDesignName>
<defaultValue>now()</defaultValue>
</ColumnProxy>
<ColumnProxy name="transaccion" id="42026148-5C20-58E7-6EAC-108561B5F6B3">
<createdBy>systech59</createdBy>
<createdTime>2023-02-07 03:16:07 UTC</createdTime>
<ownerDesignName>suite</ownerDesignName>
</ColumnProxy>
<ColumnProxy name="oid" id="8096FCFF-1519-8196-B1DD-DD5C9E99319A">
<createdBy>systech59</createdBy>
<createdTime>2023-02-07 03:16:07 UTC</createdTime>
<ownerDesignName>suite</ownerDesignName>
<defaultValue>nextval(&apos;transacciones_anulaciones_oid_seq&apos;::regclass)</defaultValue>
</ColumnProxy>
<ColumnProxy name="usuario_insercion" id="C9163CCD-4983-6FAC-06BE-0979C7F774E5">
<createdBy>systech59</createdBy>
<createdTime>2023-02-07 03:16:07 UTC</createdTime>
<ownerDesignName>suite</ownerDesignName>
</ColumnProxy>
<ColumnProxy name="interfaz" id="EBD4D86D-3039-3A49-335B-BDF69FE55218">
<createdBy>systech59</createdBy>
<createdTime>2023-02-07 03:16:07 UTC</createdTime>
<ownerDesignName>suite</ownerDesignName>
<defaultValue>(&apos;N&apos;::character varying)::decision_n_s</defaultValue>
</ColumnProxy>
</columnProxies>
<indexProxies>
<IndexProxy class="oracle.dbtools.crest.model.design.storage.oracle.v10g.IndexProxyOraclev10g" name="tran_conta_tran_fk" id="919648E0-0D37-C4A3-2DDE-287067237452">
<createdBy>systech59</createdBy>
<createdTime>2023-02-07 03:16:08 UTC</createdTime>
<ownerDesignName>suite</ownerDesignName>
</IndexProxy>
<IndexProxy class="oracle.dbtools.crest.model.design.storage.oracle.v10g.IndexProxyOraclev10g" name="tran_conta_tran_anul_fk" id="C7044EA6-51BA-3CD5-BC86-000F2B460DE9">
<createdBy>systech59</createdBy>
<createdTime>2023-02-07 03:16:08 UTC</createdTime>
<ownerDesignName>suite</ownerDesignName>
</IndexProxy>
</indexProxies>
<foreignKeys>
<ForeignKey class="oracle.dbtools.crest.model.design.storage.oracle.v10g.FKProxyOraclev10g" name="tran_conta_tran_fk" id="AC263A5E-D812-DFBD-1C72-0274671CA8D5">
<createdBy>systech59</createdBy>
<createdTime>2023-02-07 03:16:08 UTC</createdTime>
<ownerDesignName>suite</ownerDesignName>
</ForeignKey>
<ForeignKey class="oracle.dbtools.crest.model.design.storage.oracle.v10g.FKProxyOraclev10g" name="tran_conta_tran_anul_fk" id="FCA6A84C-CEC5-7D79-2D47-743D2F78052D">
<createdBy>systech59</createdBy>
<createdTime>2023-02-07 03:16:08 UTC</createdTime>
<ownerDesignName>suite</ownerDesignName>
</ForeignKey>
</foreignKeys>
<primaryKeys>
<PrimaryKey class="oracle.dbtools.crest.model.design.storage.oracle.v10g.PKProxyOraclev10g" name="tran_anul_pk" id="E9C7AC6D-A870-87A5-A78C-E5EE1BFD053A">
<createdBy>systech59</createdBy>
<createdTime>2023-02-07 03:16:08 UTC</createdTime>
<ownerDesignName>suite</ownerDesignName>
<indexSort>SORTED</indexSort>
</PrimaryKey>
</primaryKeys>
<tableCheckConstraints itemClass="oracle.dbtools.crest.model.design.storage.oracle.TableCheckConstraintOracle">
<TableCheckConstraint name="usua_inse_ck_0305" id="D216DD04-9941-1FC5-DB5F-63961BF49862">
<createdBy>systech59</createdBy>
<createdTime>2023-02-07 03:16:08 UTC</createdTime>
<ownerDesignName>suite</ownerDesignName>
</TableCheckConstraint>
<TableCheckConstraint name="avcon_1138891234_trans_093" id="E00120B8-008C-AF7B-AE9F-13D247D5A57F">
<createdBy>systech59</createdBy>
<createdTime>2023-02-07 03:16:08 UTC</createdTime>
<ownerDesignName>suite</ownerDesignName>
</TableCheckConstraint>
</tableCheckConstraints>
<uniqueKeys>
<UniqueKey class="oracle.dbtools.crest.model.design.storage.oracle.v10g.UniqueOraclev10g" name="transacciones_anulaciones_oid" id="47F7D7A0-827F-C8A3-1588-103B53FE688A">
<createdBy>systech59</createdBy>
<createdTime>2023-02-07 03:16:08 UTC</createdTime>
<ownerDesignName>suite</ownerDesignName>
<indexSort>SORTED</indexSort>
</UniqueKey>
</uniqueKeys>
</TableProxyOraclev11g>