<?xml version = '1.0' encoding = 'UTF-8'?>
<FKIndexAssociation class="oracle.dbtools.crest.model.design.relational.FKIndexAssociation" directorySegmentName="seg_2" id="289C4DED-27E9-51A5-F17F-FFF10B6F82D4" containerWithKeyObject="688AB39A-6BEB-F46B-46B4-4585B2D02465" localFKIndex="EB488DE6-E195-6821-C4CC-EF379DB3C8F8" name="desc_clie_desc_fk">
<sourceConnName>postgres</sourceConnName>
<sourceObjSchema>public</sourceObjSchema>
<sourceObjName>desc_clie_desc_fk</sourceObjName>
<createdBy>systech59</createdBy>
<createdTime>2023-02-07 03:15:58 UTC</createdTime>
<ownerDesignName>suite</ownerDesignName>
<referredTableLongName>public.descuentos</referredTableLongName>
<deleteRule>NO ACTION</deleteRule>
<referredTableID>DC779895-6BDB-6B63-5FB2-B789B4303AEF</referredTableID>
<keyObject>EF107DF1-11B9-D707-B403-DFEB1B3A8D48</keyObject>
<referredKeyID>EF107DF1-11B9-D707-B403-DFEB1B3A8D48</referredKeyID>
<mandatory>true</mandatory>
<refColNames>tipo_descuento,descuento</refColNames>
<transferable>true</transferable>
<rely>false</rely>
<columnDependencyConstraintGenerateInDDL>true</columnDependencyConstraintGenerateInDDL>
</FKIndexAssociation>