<?xml version = '1.0' encoding = 'UTF-8'?>
<FKIndexAssociation class="oracle.dbtools.crest.model.design.relational.FKIndexAssociation" directorySegmentName="seg_3" id="CB5DE0CA-2E4A-BBBF-C75A-0AB6AC7383A2" containerWithKeyObject="0F530E5C-4F34-DAED-E2E0-BDDAA2B2AD13" localFKIndex="01F6AF06-A5F6-790F-CB65-768CF71C8625" name="desp_tras_punt_dest_fk">
<sourceConnName>postgres</sourceConnName>
<sourceObjSchema>public</sourceObjSchema>
<sourceObjName>desp_tras_punt_dest_fk</sourceObjName>
<createdBy>systech59</createdBy>
<createdTime>2023-02-07 03:15:58 UTC</createdTime>
<ownerDesignName>suite</ownerDesignName>
<referredTableLongName>public.puntos</referredTableLongName>
<deleteRule>NO ACTION</deleteRule>
<referredTableID>AB83264C-17F7-887F-B861-F045F1CECADE</referredTableID>
<keyObject>8F0A073E-BE3A-5EC9-6568-9520A73D01BC</keyObject>
<referredKeyID>8F0A073E-BE3A-5EC9-6568-9520A73D01BC</referredKeyID>
<mandatory>true</mandatory>
<refColNames>punto</refColNames>
<transferable>true</transferable>
<rely>false</rely>
<columnDependencyConstraintGenerateInDDL>true</columnDependencyConstraintGenerateInDDL>
</FKIndexAssociation>