<?xml version = '1.0' encoding = 'UTF-8'?>
<TableProxyOraclev20c class="oracle.dbtools.crest.model.design.storage.oracle.v20c.TableProxyOraclev20c" name="tratos" directorySegmentName="seg_0" id="5DF0C32F-FE20-1345-8371-EF232275F30C">
<createdBy>systech59</createdBy>
<createdTime>2022-06-21 21:46:44 UTC</createdTime>
<ownerDesignName>crm</ownerDesignName>
<logging>YES</logging>
<partitionedRowMovement>DISABLE</partitionedRowMovement>
<temporaryChanged>false</temporaryChanged>
<accessDriverType>oracle_loader</accessDriverType>
<rejectLimit></rejectLimit>
<columnProxies itemClass="oracle.dbtools.crest.model.design.storage.oracle.v12c.ColumnProxyOraclev12c">
<ColumnProxy name="fecha_insercion" id="0DD115ED-3A9F-A3FD-6BAF-FEA79E63A19A">
<createdBy>systech59</createdBy>
<createdTime>2022-06-21 21:49:48 UTC</createdTime>
<ownerDesignName>crm</ownerDesignName>
<defaultValue>datetime</defaultValue>
</ColumnProxy>
<ColumnProxy name="id_trato" id="4B8A521D-D803-FA82-CF71-4DE3ED5B95A1">
<createdBy>systech59</createdBy>
<createdTime>2022-06-21 21:47:20 UTC</createdTime>
<ownerDesignName>crm</ownerDesignName>
</ColumnProxy>
<ColumnProxy name="id_usuario_modificacion" id="800CC131-BAD0-89A8-D003-7C1D9685D73A">
<createdBy>systech59</createdBy>
<createdTime>2022-06-21 21:49:48 UTC</createdTime>
<ownerDesignName>crm</ownerDesignName>
</ColumnProxy>
<ColumnProxy name="id_usuario_insercion" id="8A27E154-E85D-D0A9-C398-81811525A424">
<createdBy>systech59</createdBy>
<createdTime>2022-06-21 21:49:48 UTC</createdTime>
<ownerDesignName>crm</ownerDesignName>
</ColumnProxy>
<ColumnProxy name="fecha_modificacion" id="90917613-2A69-1B3E-6583-E1FE0E2CA316">
<createdBy>systech59</createdBy>
<createdTime>2022-06-21 21:49:48 UTC</createdTime>
<ownerDesignName>crm</ownerDesignName>
<defaultValue>datetime</defaultValue>
</ColumnProxy>
<ColumnProxy name="trato" id="9D7CA06C-587A-52B3-62F0-C75227D239F4">
<createdBy>systech59</createdBy>
<createdTime>2022-06-21 21:48:16 UTC</createdTime>
<ownerDesignName>crm</ownerDesignName>
</ColumnProxy>
<ColumnProxy name="nombre" id="BE86BE0E-3659-ED7F-88C0-6415338DD2D6">
<createdBy>systech59</createdBy>
<createdTime>2022-06-21 21:51:56 UTC</createdTime>
<ownerDesignName>crm</ownerDesignName>
</ColumnProxy>
</columnProxies>
<foreignKeys>
<ForeignKey class="oracle.dbtools.crest.model.design.storage.oracle.v10g.FKProxyOraclev10g" name="tratos_usuarios_FK" id="06206656-F3F7-3C53-C718-5DAC8798BAED">
<createdBy>systech59</createdBy>
<createdTime>2022-06-21 21:53:04 UTC</createdTime>
<ownerDesignName>crm</ownerDesignName>
</ForeignKey>
<ForeignKey class="oracle.dbtools.crest.model.design.storage.oracle.v10g.FKProxyOraclev10g" name="tratos_usuarios_FKv1" id="CE1F7285-2AC3-106F-1A24-72CA8C55F4A6">
<createdBy>systech59</createdBy>
<createdTime>2022-06-21 21:55:00 UTC</createdTime>
<ownerDesignName>crm</ownerDesignName>
</ForeignKey>
</foreignKeys>
<primaryKeys>
<PrimaryKey class="oracle.dbtools.crest.model.design.storage.oracle.v10g.PKProxyOraclev10g" name="tratos_PK" id="F2FCD453-6266-589B-2773-F08B8910F719">
<createdBy>systech59</createdBy>
<createdTime>2022-06-21 21:47:20 UTC</createdTime>
<ownerDesignName>crm</ownerDesignName>
<indexSort>SORTED</indexSort>
</PrimaryKey>
</primaryKeys>
<uniqueKeys>
<UniqueKey class="oracle.dbtools.crest.model.design.storage.oracle.v10g.UniqueOraclev10g" name="tratos__UN" id="07A1D99B-A943-6B59-64A6-33F9D75ACA1C">
<createdBy>systech59</createdBy>
<createdTime>2022-06-21 21:51:16 UTC</createdTime>
<ownerDesignName>crm</ownerDesignName>
<indexSort>SORTED</indexSort>
</UniqueKey>
</uniqueKeys>
</TableProxyOraclev20c>